sammen/__init__.py
sammen/__main__.py
sammen/cli.py
sammen/sammen.py
sammen-2023.10.21.dist-info/LICENSE
sammen-2023.10.21.dist-info/METADATA
sammen-2023.10.21.dist-info/WHEEL
sammen-2023.10.21.dist-info/entry_points.txt
sammen-2023.10.21.dist-info/top_level.txt
sammen-2023.10.21.dist-info/RECORD
