Metadata-Version: 2.1
Name: sammen
Version: 2023.10.21
Summary: Dansk for together - multiple watch to ensure special events come together or go away.
Author-email: Stefan Hagen <stefan@hagen.link>
Maintainer-email: Stefan Hagen <stefan@hagen.link>
Project-URL: Homepage, https://git.sr.ht/~sthagen/sammen
Project-URL: Bug-Tracker, https://todo.sr.ht/~sthagen/sammen
Project-URL: Documentation, https://codes.dilettant.life/docs/sammen
Project-URL: Source-Code, https://git.sr.ht/~sthagen/sammen
Project-URL: Test-Coverage, https://codes.dilettant.life/coverage/sammen
Keywords: developer-tools,devops
Classifier: Development Status :: 3 - Alpha
Classifier: Intended Audience :: Developers
Classifier: License :: OSI Approved :: MIT License
Classifier: Programming Language :: Python :: 3.10
Classifier: Programming Language :: Python :: 3.11
Classifier: Programming Language :: Python :: 3.9
Requires-Python: >=3.9
License-File: LICENSE
Requires-Dist: watchfiles >=0.21.0
Provides-Extra: dev
Requires-Dist: black ; extra == 'dev'
Requires-Dist: coverage ; extra == 'dev'
Requires-Dist: hypothesis ; extra == 'dev'
Requires-Dist: mypy ; extra == 'dev'
Requires-Dist: pytest ; extra == 'dev'
Requires-Dist: pytest-cov ; extra == 'dev'
Requires-Dist: pytest-flake8 ; extra == 'dev'
Requires-Dist: ruff ; extra == 'dev'
